<?xml version="1.0" encoding="UTF-8"?>
<!DOCTYPE mapper PUBLIC "-//mybatis.org//DTD Mapper 3.0//EN" "http://mybatis.org/dtd/mybatis-3-mapper.dtd">
<mapper namespace="com.fit2cloud.oss.base.mapper.FsXskyFolderMapper">
  <resultMap id="BaseResultMap" type="com.fit2cloud.oss.base.domain.FsXskyFolder">
    <!--
      WARNING - @mbg.generated
      This element is automatically generated by MyBatis Generator, do not modify.
    -->
    <id column="id" jdbcType="INTEGER" property="id" />
    <result column="name" jdbcType="VARCHAR" property="name" />
    <result column="folder_id" jdbcType="BIGINT" property="folderId" />
    <result column="access_member_num" jdbcType="BIGINT" property="accessMemberNum" />
    <result column="access_path_name" jdbcType="VARCHAR" property="accessPathName" />
    <result column="action_status" jdbcType="VARCHAR" property="actionStatus" />
    <result column="fs_quota_tree_num" jdbcType="BIGINT" property="fsQuotaTreeNum" />
    <result column="pool_name" jdbcType="VARCHAR" property="poolName" />
    <result column="pool_id" jdbcType="BIGINT" property="poolId" />
    <result column="gateway_group_name" jdbcType="VARCHAR" property="gatewayGroupName" />
    <result column="gateway_group_id" jdbcType="BIGINT" property="gatewayGroupId" />
    <result column="status" jdbcType="VARCHAR" property="status" />
    <result column="shared" jdbcType="BIT" property="shared" />
    <result column="size" jdbcType="BIGINT" property="size" />
    <result column="used_kbyte" jdbcType="DOUBLE" property="usedKbyte" />
    <result column="total_bandwidth_kbyte" jdbcType="DOUBLE" property="totalBandwidthKbyte" />
    <result column="total_iops" jdbcType="DOUBLE" property="totalIops" />
    <result column="description" jdbcType="VARCHAR" property="description" />
    <result column="share_types" jdbcType="VARCHAR" property="shareTypes" />
    <result column="account_id" jdbcType="VARCHAR" property="accountId" />
    <result column="workspace" jdbcType="VARCHAR" property="workspace" />
    <result column="organization" jdbcType="VARCHAR" property="organization" />
    <result column="create_time" jdbcType="BIGINT" property="createTime" />
    <result column="update_time" jdbcType="BIGINT" property="updateTime" />
  </resultMap>
  <sql id="Example_Where_Clause">
    <!--
      WARNING - @mbg.generated
      This element is automatically generated by MyBatis Generator, do not modify.
    -->
    <where>
      <foreach collection="oredCriteria" item="criteria" separator="or">
        <if test="criteria.valid">
          <trim prefix="(" prefixOverrides="and" suffix=")">
            <foreach collection="criteria.criteria" item="criterion">
              <choose>
                <when test="criterion.noValue">
                  and ${criterion.condition}
                </when>
                <when test="criterion.singleValue">
                  and ${criterion.condition} #{criterion.value}
                </when>
                <when test="criterion.betweenValue">
                  and ${criterion.condition} #{criterion.value} and #{criterion.secondValue}
                </when>
                <when test="criterion.listValue">
                  and ${criterion.condition}
                  <foreach close=")" collection="criterion.value" item="listItem" open="(" separator=",">
                    #{listItem}
                  </foreach>
                </when>
              </choose>
            </foreach>
          </trim>
        </if>
      </foreach>
    </where>
  </sql>
  <sql id="Update_By_Example_Where_Clause">
    <!--
      WARNING - @mbg.generated
      This element is automatically generated by MyBatis Generator, do not modify.
    -->
    <where>
      <foreach collection="example.oredCriteria" item="criteria" separator="or">
        <if test="criteria.valid">
          <trim prefix="(" prefixOverrides="and" suffix=")">
            <foreach collection="criteria.criteria" item="criterion">
              <choose>
                <when test="criterion.noValue">
                  and ${criterion.condition}
                </when>
                <when test="criterion.singleValue">
                  and ${criterion.condition} #{criterion.value}
                </when>
                <when test="criterion.betweenValue">
                  and ${criterion.condition} #{criterion.value} and #{criterion.secondValue}
                </when>
                <when test="criterion.listValue">
                  and ${criterion.condition}
                  <foreach close=")" collection="criterion.value" item="listItem" open="(" separator=",">
                    #{listItem}
                  </foreach>
                </when>
              </choose>
            </foreach>
          </trim>
        </if>
      </foreach>
    </where>
  </sql>
  <sql id="Base_Column_List">
    <!--
      WARNING - @mbg.generated
      This element is automatically generated by MyBatis Generator, do not modify.
    -->
    id, name, folder_id, access_member_num, access_path_name, action_status, fs_quota_tree_num, 
    pool_name, pool_id, gateway_group_name, gateway_group_id, status, shared, size, used_kbyte, 
    total_bandwidth_kbyte, total_iops, description, share_types, account_id, workspace, 
    organization, create_time, update_time
  </sql>
  <select id="selectByExample" parameterType="com.fit2cloud.oss.base.domain.FsXskyFolderExample" resultMap="BaseResultMap">
    <!--
      WARNING - @mbg.generated
      This element is automatically generated by MyBatis Generator, do not modify.
    -->
    select
    <if test="distinct">
      distinct
    </if>
    <include refid="Base_Column_List" />
    from fs_xsky_folder
    <if test="_parameter != null">
      <include refid="Example_Where_Clause" />
    </if>
    <if test="orderByClause != null">
      order by ${orderByClause}
    </if>
  </select>
  <select id="selectByPrimaryKey" parameterType="java.lang.Integer" resultMap="BaseResultMap">
    <!--
      WARNING - @mbg.generated
      This element is automatically generated by MyBatis Generator, do not modify.
    -->
    select 
    <include refid="Base_Column_List" />
    from fs_xsky_folder
    where id = #{id,jdbcType=INTEGER}
  </select>
  <delete id="deleteByPrimaryKey" parameterType="java.lang.Integer">
    <!--
      WARNING - @mbg.generated
      This element is automatically generated by MyBatis Generator, do not modify.
    -->
    delete from fs_xsky_folder
    where id = #{id,jdbcType=INTEGER}
  </delete>
  <delete id="deleteByExample" parameterType="com.fit2cloud.oss.base.domain.FsXskyFolderExample">
    <!--
      WARNING - @mbg.generated
      This element is automatically generated by MyBatis Generator, do not modify.
    -->
    delete from fs_xsky_folder
    <if test="_parameter != null">
      <include refid="Example_Where_Clause" />
    </if>
  </delete>
  <insert id="insert" parameterType="com.fit2cloud.oss.base.domain.FsXskyFolder">
    <!--
      WARNING - @mbg.generated
      This element is automatically generated by MyBatis Generator, do not modify.
    -->
    insert into fs_xsky_folder (id, name, folder_id, 
      access_member_num, access_path_name, action_status, 
      fs_quota_tree_num, pool_name, pool_id, 
      gateway_group_name, gateway_group_id, status, 
      shared, size, used_kbyte, 
      total_bandwidth_kbyte, total_iops, description, 
      share_types, account_id, workspace, 
      organization, create_time, update_time
      )
    values (#{id,jdbcType=INTEGER}, #{name,jdbcType=VARCHAR}, #{folderId,jdbcType=BIGINT}, 
      #{accessMemberNum,jdbcType=BIGINT}, #{accessPathName,jdbcType=VARCHAR}, #{actionStatus,jdbcType=VARCHAR}, 
      #{fsQuotaTreeNum,jdbcType=BIGINT}, #{poolName,jdbcType=VARCHAR}, #{poolId,jdbcType=BIGINT}, 
      #{gatewayGroupName,jdbcType=VARCHAR}, #{gatewayGroupId,jdbcType=BIGINT}, #{status,jdbcType=VARCHAR}, 
      #{shared,jdbcType=BIT}, #{size,jdbcType=BIGINT}, #{usedKbyte,jdbcType=DOUBLE}, 
      #{totalBandwidthKbyte,jdbcType=DOUBLE}, #{totalIops,jdbcType=DOUBLE}, #{description,jdbcType=VARCHAR}, 
      #{shareTypes,jdbcType=VARCHAR}, #{accountId,jdbcType=VARCHAR}, #{workspace,jdbcType=VARCHAR}, 
      #{organization,jdbcType=VARCHAR}, #{createTime,jdbcType=BIGINT}, #{updateTime,jdbcType=BIGINT}
      )
  </insert>
  <insert id="insertSelective" parameterType="com.fit2cloud.oss.base.domain.FsXskyFolder">
    <!--
      WARNING - @mbg.generated
      This element is automatically generated by MyBatis Generator, do not modify.
    -->
    insert into fs_xsky_folder
    <trim prefix="(" suffix=")" suffixOverrides=",">
      <if test="id != null">
        id,
      </if>
      <if test="name != null">
        name,
      </if>
      <if test="folderId != null">
        folder_id,
      </if>
      <if test="accessMemberNum != null">
        access_member_num,
      </if>
      <if test="accessPathName != null">
        access_path_name,
      </if>
      <if test="actionStatus != null">
        action_status,
      </if>
      <if test="fsQuotaTreeNum != null">
        fs_quota_tree_num,
      </if>
      <if test="poolName != null">
        pool_name,
      </if>
      <if test="poolId != null">
        pool_id,
      </if>
      <if test="gatewayGroupName != null">
        gateway_group_name,
      </if>
      <if test="gatewayGroupId != null">
        gateway_group_id,
      </if>
      <if test="status != null">
        status,
      </if>
      <if test="shared != null">
        shared,
      </if>
      <if test="size != null">
        size,
      </if>
      <if test="usedKbyte != null">
        used_kbyte,
      </if>
      <if test="totalBandwidthKbyte != null">
        total_bandwidth_kbyte,
      </if>
      <if test="totalIops != null">
        total_iops,
      </if>
      <if test="description != null">
        description,
      </if>
      <if test="shareTypes != null">
        share_types,
      </if>
      <if test="accountId != null">
        account_id,
      </if>
      <if test="workspace != null">
        workspace,
      </if>
      <if test="organization != null">
        organization,
      </if>
      <if test="createTime != null">
        create_time,
      </if>
      <if test="updateTime != null">
        update_time,
      </if>
    </trim>
    <trim prefix="values (" suffix=")" suffixOverrides=",">
      <if test="id != null">
        #{id,jdbcType=INTEGER},
      </if>
      <if test="name != null">
        #{name,jdbcType=VARCHAR},
      </if>
      <if test="folderId != null">
        #{folderId,jdbcType=BIGINT},
      </if>
      <if test="accessMemberNum != null">
        #{accessMemberNum,jdbcType=BIGINT},
      </if>
      <if test="accessPathName != null">
        #{accessPathName,jdbcType=VARCHAR},
      </if>
      <if test="actionStatus != null">
        #{actionStatus,jdbcType=VARCHAR},
      </if>
      <if test="fsQuotaTreeNum != null">
        #{fsQuotaTreeNum,jdbcType=BIGINT},
      </if>
      <if test="poolName != null">
        #{poolName,jdbcType=VARCHAR},
      </if>
      <if test="poolId != null">
        #{poolId,jdbcType=BIGINT},
      </if>
      <if test="gatewayGroupName != null">
        #{gatewayGroupName,jdbcType=VARCHAR},
      </if>
      <if test="gatewayGroupId != null">
        #{gatewayGroupId,jdbcType=BIGINT},
      </if>
      <if test="status != null">
        #{status,jdbcType=VARCHAR},
      </if>
      <if test="shared != null">
        #{shared,jdbcType=BIT},
      </if>
      <if test="size != null">
        #{size,jdbcType=BIGINT},
      </if>
      <if test="usedKbyte != null">
        #{usedKbyte,jdbcType=DOUBLE},
      </if>
      <if test="totalBandwidthKbyte != null">
        #{totalBandwidthKbyte,jdbcType=DOUBLE},
      </if>
      <if test="totalIops != null">
        #{totalIops,jdbcType=DOUBLE},
      </if>
      <if test="description != null">
        #{description,jdbcType=VARCHAR},
      </if>
      <if test="shareTypes != null">
        #{shareTypes,jdbcType=VARCHAR},
      </if>
      <if test="accountId != null">
        #{accountId,jdbcType=VARCHAR},
      </if>
      <if test="workspace != null">
        #{workspace,jdbcType=VARCHAR},
      </if>
      <if test="organization != null">
        #{organization,jdbcType=VARCHAR},
      </if>
      <if test="createTime != null">
        #{createTime,jdbcType=BIGINT},
      </if>
      <if test="updateTime != null">
        #{updateTime,jdbcType=BIGINT},
      </if>
    </trim>
  </insert>
  <select id="countByExample" parameterType="com.fit2cloud.oss.base.domain.FsXskyFolderExample" resultType="java.lang.Long">
    <!--
      WARNING - @mbg.generated
      This element is automatically generated by MyBatis Generator, do not modify.
    -->
    select count(*) from fs_xsky_folder
    <if test="_parameter != null">
      <include refid="Example_Where_Clause" />
    </if>
  </select>
  <update id="updateByExampleSelective" parameterType="map">
    <!--
      WARNING - @mbg.generated
      This element is automatically generated by MyBatis Generator, do not modify.
    -->
    update fs_xsky_folder
    <set>
      <if test="record.id != null">
        id = #{record.id,jdbcType=INTEGER},
      </if>
      <if test="record.name != null">
        name = #{record.name,jdbcType=VARCHAR},
      </if>
      <if test="record.folderId != null">
        folder_id = #{record.folderId,jdbcType=BIGINT},
      </if>
      <if test="record.accessMemberNum != null">
        access_member_num = #{record.accessMemberNum,jdbcType=BIGINT},
      </if>
      <if test="record.accessPathName != null">
        access_path_name = #{record.accessPathName,jdbcType=VARCHAR},
      </if>
      <if test="record.actionStatus != null">
        action_status = #{record.actionStatus,jdbcType=VARCHAR},
      </if>
      <if test="record.fsQuotaTreeNum != null">
        fs_quota_tree_num = #{record.fsQuotaTreeNum,jdbcType=BIGINT},
      </if>
      <if test="record.poolName != null">
        pool_name = #{record.poolName,jdbcType=VARCHAR},
      </if>
      <if test="record.poolId != null">
        pool_id = #{record.poolId,jdbcType=BIGINT},
      </if>
      <if test="record.gatewayGroupName != null">
        gateway_group_name = #{record.gatewayGroupName,jdbcType=VARCHAR},
      </if>
      <if test="record.gatewayGroupId != null">
        gateway_group_id = #{record.gatewayGroupId,jdbcType=BIGINT},
      </if>
      <if test="record.status != null">
        status = #{record.status,jdbcType=VARCHAR},
      </if>
      <if test="record.shared != null">
        shared = #{record.shared,jdbcType=BIT},
      </if>
      <if test="record.size != null">
        size = #{record.size,jdbcType=BIGINT},
      </if>
      <if test="record.usedKbyte != null">
        used_kbyte = #{record.usedKbyte,jdbcType=DOUBLE},
      </if>
      <if test="record.totalBandwidthKbyte != null">
        total_bandwidth_kbyte = #{record.totalBandwidthKbyte,jdbcType=DOUBLE},
      </if>
      <if test="record.totalIops != null">
        total_iops = #{record.totalIops,jdbcType=DOUBLE},
      </if>
      <if test="record.description != null">
        description = #{record.description,jdbcType=VARCHAR},
      </if>
      <if test="record.shareTypes != null">
        share_types = #{record.shareTypes,jdbcType=VARCHAR},
      </if>
      <if test="record.accountId != null">
        account_id = #{record.accountId,jdbcType=VARCHAR},
      </if>
      <if test="record.workspace != null">
        workspace = #{record.workspace,jdbcType=VARCHAR},
      </if>
      <if test="record.organization != null">
        organization = #{record.organization,jdbcType=VARCHAR},
      </if>
      <if test="record.createTime != null">
        create_time = #{record.createTime,jdbcType=BIGINT},
      </if>
      <if test="record.updateTime != null">
        update_time = #{record.updateTime,jdbcType=BIGINT},
      </if>
    </set>
    <if test="_parameter != null">
      <include refid="Update_By_Example_Where_Clause" />
    </if>
  </update>
  <update id="updateByExample" parameterType="map">
    <!--
      WARNING - @mbg.generated
      This element is automatically generated by MyBatis Generator, do not modify.
    -->
    update fs_xsky_folder
    set id = #{record.id,jdbcType=INTEGER},
      name = #{record.name,jdbcType=VARCHAR},
      folder_id = #{record.folderId,jdbcType=BIGINT},
      access_member_num = #{record.accessMemberNum,jdbcType=BIGINT},
      access_path_name = #{record.accessPathName,jdbcType=VARCHAR},
      action_status = #{record.actionStatus,jdbcType=VARCHAR},
      fs_quota_tree_num = #{record.fsQuotaTreeNum,jdbcType=BIGINT},
      pool_name = #{record.poolName,jdbcType=VARCHAR},
      pool_id = #{record.poolId,jdbcType=BIGINT},
      gateway_group_name = #{record.gatewayGroupName,jdbcType=VARCHAR},
      gateway_group_id = #{record.gatewayGroupId,jdbcType=BIGINT},
      status = #{record.status,jdbcType=VARCHAR},
      shared = #{record.shared,jdbcType=BIT},
      size = #{record.size,jdbcType=BIGINT},
      used_kbyte = #{record.usedKbyte,jdbcType=DOUBLE},
      total_bandwidth_kbyte = #{record.totalBandwidthKbyte,jdbcType=DOUBLE},
      total_iops = #{record.totalIops,jdbcType=DOUBLE},
      description = #{record.description,jdbcType=VARCHAR},
      share_types = #{record.shareTypes,jdbcType=VARCHAR},
      account_id = #{record.accountId,jdbcType=VARCHAR},
      workspace = #{record.workspace,jdbcType=VARCHAR},
      organization = #{record.organization,jdbcType=VARCHAR},
      create_time = #{record.createTime,jdbcType=BIGINT},
      update_time = #{record.updateTime,jdbcType=BIGINT}
    <if test="_parameter != null">
      <include refid="Update_By_Example_Where_Clause" />
    </if>
  </update>
  <update id="updateByPrimaryKeySelective" parameterType="com.fit2cloud.oss.base.domain.FsXskyFolder">
    <!--
      WARNING - @mbg.generated
      This element is automatically generated by MyBatis Generator, do not modify.
    -->
    update fs_xsky_folder
    <set>
      <if test="name != null">
        name = #{name,jdbcType=VARCHAR},
      </if>
      <if test="folderId != null">
        folder_id = #{folderId,jdbcType=BIGINT},
      </if>
      <if test="accessMemberNum != null">
        access_member_num = #{accessMemberNum,jdbcType=BIGINT},
      </if>
      <if test="accessPathName != null">
        access_path_name = #{accessPathName,jdbcType=VARCHAR},
      </if>
      <if test="actionStatus != null">
        action_status = #{actionStatus,jdbcType=VARCHAR},
      </if>
      <if test="fsQuotaTreeNum != null">
        fs_quota_tree_num = #{fsQuotaTreeNum,jdbcType=BIGINT},
      </if>
      <if test="poolName != null">
        pool_name = #{poolName,jdbcType=VARCHAR},
      </if>
      <if test="poolId != null">
        pool_id = #{poolId,jdbcType=BIGINT},
      </if>
      <if test="gatewayGroupName != null">
        gateway_group_name = #{gatewayGroupName,jdbcType=VARCHAR},
      </if>
      <if test="gatewayGroupId != null">
        gateway_group_id = #{gatewayGroupId,jdbcType=BIGINT},
      </if>
      <if test="status != null">
        status = #{status,jdbcType=VARCHAR},
      </if>
      <if test="shared != null">
        shared = #{shared,jdbcType=BIT},
      </if>
      <if test="size != null">
        size = #{size,jdbcType=BIGINT},
      </if>
      <if test="usedKbyte != null">
        used_kbyte = #{usedKbyte,jdbcType=DOUBLE},
      </if>
      <if test="totalBandwidthKbyte != null">
        total_bandwidth_kbyte = #{totalBandwidthKbyte,jdbcType=DOUBLE},
      </if>
      <if test="totalIops != null">
        total_iops = #{totalIops,jdbcType=DOUBLE},
      </if>
      <if test="description != null">
        description = #{description,jdbcType=VARCHAR},
      </if>
      <if test="shareTypes != null">
        share_types = #{shareTypes,jdbcType=VARCHAR},
      </if>
      <if test="accountId != null">
        account_id = #{accountId,jdbcType=VARCHAR},
      </if>
      <if test="workspace != null">
        workspace = #{workspace,jdbcType=VARCHAR},
      </if>
      <if test="organization != null">
        organization = #{organization,jdbcType=VARCHAR},
      </if>
      <if test="createTime != null">
        create_time = #{createTime,jdbcType=BIGINT},
      </if>
      <if test="updateTime != null">
        update_time = #{updateTime,jdbcType=BIGINT},
      </if>
    </set>
    where id = #{id,jdbcType=INTEGER}
  </update>
  <update id="updateByPrimaryKey" parameterType="com.fit2cloud.oss.base.domain.FsXskyFolder">
    <!--
      WARNING - @mbg.generated
      This element is automatically generated by MyBatis Generator, do not modify.
    -->
    update fs_xsky_folder
    set name = #{name,jdbcType=VARCHAR},
      folder_id = #{folderId,jdbcType=BIGINT},
      access_member_num = #{accessMemberNum,jdbcType=BIGINT},
      access_path_name = #{accessPathName,jdbcType=VARCHAR},
      action_status = #{actionStatus,jdbcType=VARCHAR},
      fs_quota_tree_num = #{fsQuotaTreeNum,jdbcType=BIGINT},
      pool_name = #{poolName,jdbcType=VARCHAR},
      pool_id = #{poolId,jdbcType=BIGINT},
      gateway_group_name = #{gatewayGroupName,jdbcType=VARCHAR},
      gateway_group_id = #{gatewayGroupId,jdbcType=BIGINT},
      status = #{status,jdbcType=VARCHAR},
      shared = #{shared,jdbcType=BIT},
      size = #{size,jdbcType=BIGINT},
      used_kbyte = #{usedKbyte,jdbcType=DOUBLE},
      total_bandwidth_kbyte = #{totalBandwidthKbyte,jdbcType=DOUBLE},
      total_iops = #{totalIops,jdbcType=DOUBLE},
      description = #{description,jdbcType=VARCHAR},
      share_types = #{shareTypes,jdbcType=VARCHAR},
      account_id = #{accountId,jdbcType=VARCHAR},
      workspace = #{workspace,jdbcType=VARCHAR},
      organization = #{organization,jdbcType=VARCHAR},
      create_time = #{createTime,jdbcType=BIGINT},
      update_time = #{updateTime,jdbcType=BIGINT}
    where id = #{id,jdbcType=INTEGER}
  </update>
</mapper>